{
    "filename": "2/000037.jpg",
    "height": 3008,
    "width": 4128,
    "annots": [
        {
            "personID": 0,
            "bbox": [544.75, 395.40, 1008.83, 1590.08, 0.84],
            "bbox_handl2d": [0.00, 0.00, 100.00, 100.00, 0.00],
            "bbox_handr2d": [0.00, 0.00, 100.00, 100.00, 0.00],
            "keypoints": [
              [ 617.27,  532.73,    1.00], 
              [ 671.23,  592.33,    1.00], 
              [ 609.36,  584.81,    1.00], 
              [ 670.24,  723.34,    0.00], 
              [ 642.18,  740.02,    0.00], 
              [ 733.10,  599.85,    1.00], 
              [ 816.68,  810.12,    0.89], 
              [ 751.80,  927.49,    0.63], 
              [ 855.12,  857.77,    1.00], 
              [ 810.01,  863.47,    1.00], 
              [ 751.43, 1125.60,    0.00], 
              [ 775.31, 1417.31,    0.41], 
              [ 900.24,  852.07,    1.00], 
              [ 849.10, 1139.40,    0.70], 
              [ 934.17, 1436.56,    0.88], 
              [ 592.39,  503.45,    1.00], 
              [ 635.13,  494.96,    1.00], 
              [ 583.42,  505.85,    1.00], 
              [ 650.69,  499.86,    1.00], 
              [ 855.69, 1490.52,    0.90], 
              [ 855.69, 1490.52,    0.90], 
              [ 970.16, 1484.99,    0.73], 
              [ 661.06, 1465.05,    0.54], 
              [ 661.06, 1465.05,    0.54], 
              [ 818.10, 1459.41,    0.40]
            ],
            "handl2d": [
              [   0.00,    0.00,    0.00], 
              [   0.00,    0.00,    0.00], 
              [   0.00,    0.00,    0.00], 
              [   0.00,    0.00,    0.00], 
              [   0.00,    0.00,    0.00], 
              [   0.00,    0.00,    0.00], 
              [   0.00,    0.00,    0.00], 
              [   0.00,    0.00,    0.00], 
              [   0.00,    0.00,    0.00], 
              [   0.00,    0.00,    0.00], 
              [   0.00,    0.00,    0.00], 
              [   0.00,    0.00,    0.00], 
              [   0.00,    0.00,    0.00], 
              [   0.00,    0.00,    0.00], 
              [   0.00,    0.00,    0.00], 
              [   0.00,    0.00,    0.00], 
              [   0.00,    0.00,    0.00], 
              [   0.00,    0.00,    0.00], 
              [   0.00,    0.00,    0.00], 
              [   0.00,    0.00,    0.00], 
              [   0.00,    0.00,    0.00]
            ],
            "handr2d": [
              [   0.00,    0.00,    0.00], 
              [   0.00,    0.00,    0.00], 
              [   0.00,    0.00,    0.00], 
              [   0.00,    0.00,    0.00], 
              [   0.00,    0.00,    0.00], 
              [   0.00,    0.00,    0.00], 
              [   0.00,    0.00,    0.00], 
              [   0.00,    0.00,    0.00], 
              [   0.00,    0.00,    0.00], 
              [   0.00,    0.00,    0.00], 
              [   0.00,    0.00,    0.00], 
              [   0.00,    0.00,    0.00], 
              [   0.00,    0.00,    0.00], 
              [   0.00,    0.00,    0.00], 
              [   0.00,    0.00,    0.00], 
              [   0.00,    0.00,    0.00], 
              [   0.00,    0.00,    0.00], 
              [   0.00,    0.00,    0.00], 
              [   0.00,    0.00,    0.00], 
              [   0.00,    0.00,    0.00], 
              [   0.00,    0.00,    0.00]
            ],
            "isKeyframe": false
        }
    ],
    "isKeyframe": false
}

