{
    "filename": "1/000295.jpg",
    "height": 3008,
    "width": 4128,
    "annots": [
        {
            "personID": 0,
            "bbox": [1928.11, 1797.44, 2313.68, 3004.79, 0.78],
            "bbox_handl2d": [0.00, 0.00, 100.00, 100.00, 0.00],
            "bbox_handr2d": [2126.29, 2270.45, 2188.07, 2341.94, 1.00],
            "bbox_face2d": [0.00, 0.00, 100.00, 100.00, 0.00],
            "keypoints": [
              [2281.55, 1917.58,    1.00], 
              [2206.68, 2020.47,    1.00], 
              [2183.94, 2019.90,    1.00], 
              [2073.55, 2132.88,    0.78], 
              [2140.46, 2264.80,    0.45], 
              [2229.42, 2021.03,    1.00], 
              [2178.85, 2181.97,    0.05], 
              [2184.21, 2323.33,    0.04], 
              [1988.29, 2306.18,    1.00], 
              [1960.24, 2313.53,    1.00], 
              [2151.52, 2541.96,    0.93], 
              [2060.09, 2811.67,    0.90], 
              [2016.33, 2298.83,    1.00], 
              [2161.87, 2537.04,    0.16], 
              [2083.64, 2800.19,    0.34], 
              [2273.14, 1898.33,    1.00], 
              [2275.50, 1898.05,    1.00], 
              [2255.65, 1908.19,    1.00], 
              [2264.04, 1909.36,    1.00], 
              [2141.14, 2875.00,    0.37], 
              [2141.14, 2875.00,    0.37], 
              [2049.85, 2837.54,    0.31], 
              [2137.09, 2904.18,    0.81], 
              [2137.09, 2904.18,    0.81], 
              [2015.53, 2848.21,    0.72]
            ],
            "handl2d": [
              [   0.00,    0.00,    0.00], 
              [   0.00,    0.00,    0.00], 
              [   0.00,    0.00,    0.00], 
              [   0.00,    0.00,    0.00], 
              [   0.00,    0.00,    0.00], 
              [   0.00,    0.00,    0.00], 
              [   0.00,    0.00,    0.00], 
              [   0.00,    0.00,    0.00], 
              [   0.00,    0.00,    0.00], 
              [   0.00,    0.00,    0.00], 
              [   0.00,    0.00,    0.00], 
              [   0.00,    0.00,    0.00], 
              [   0.00,    0.00,    0.00], 
              [   0.00,    0.00,    0.00], 
              [   0.00,    0.00,    0.00], 
              [   0.00,    0.00,    0.00], 
              [   0.00,    0.00,    0.00], 
              [   0.00,    0.00,    0.00], 
              [   0.00,    0.00,    0.00], 
              [   0.00,    0.00,    0.00], 
              [   0.00,    0.00,    0.00]
            ],
            "handr2d": [
              [2150.21, 2305.71,    1.00], 
              [2161.70, 2290.83,    1.00], 
              [2169.06, 2280.39,    1.00], 
              [2161.61, 2276.41,    1.00], 
              [2150.03, 2279.31,    1.00], 
              [2182.92, 2304.03,    1.00], 
              [2159.69, 2289.20,    1.00], 
              [2158.61, 2285.55,    1.00], 
              [2164.11, 2288.14,    1.00], 
              [2168.13, 2318.55,    1.00], 
              [2153.99, 2308.38,    1.00], 
              [2153.48, 2305.19,    1.00], 
              [2155.67, 2306.33,    1.00], 
              [2152.28, 2329.05,    1.00], 
              [2141.69, 2319.70,    1.00], 
              [2141.08, 2315.93,    1.00], 
              [2144.61, 2318.35,    1.00], 
              [2137.00, 2335.99,    1.00], 
              [2132.64, 2330.52,    1.00], 
              [2131.44, 2326.75,    1.00], 
              [2132.42, 2329.41,    1.00]
            ],
            "face2d": [
              [   0.00,    0.00,    0.00], 
              [   0.00,    0.00,    0.00], 
              [   0.00,    0.00,    0.00], 
              [   0.00,    0.00,    0.00], 
              [   0.00,    0.00,    0.00], 
              [   0.00,    0.00,    0.00], 
              [   0.00,    0.00,    0.00], 
              [   0.00,    0.00,    0.00], 
              [   0.00,    0.00,    0.00], 
              [   0.00,    0.00,    0.00], 
              [   0.00,    0.00,    0.00], 
              [   0.00,    0.00,    0.00], 
              [   0.00,    0.00,    0.00], 
              [   0.00,    0.00,    0.00], 
              [   0.00,    0.00,    0.00], 
              [   0.00,    0.00,    0.00], 
              [   0.00,    0.00,    0.00], 
              [   0.00,    0.00,    0.00], 
              [   0.00,    0.00,    0.00], 
              [   0.00,    0.00,    0.00], 
              [   0.00,    0.00,    0.00], 
              [   0.00,    0.00,    0.00], 
              [   0.00,    0.00,    0.00], 
              [   0.00,    0.00,    0.00], 
              [   0.00,    0.00,    0.00], 
              [   0.00,    0.00,    0.00], 
              [   0.00,    0.00,    0.00], 
              [   0.00,    0.00,    0.00], 
              [   0.00,    0.00,    0.00], 
              [   0.00,    0.00,    0.00], 
              [   0.00,    0.00,    0.00], 
              [   0.00,    0.00,    0.00], 
              [   0.00,    0.00,    0.00], 
              [   0.00,    0.00,    0.00], 
              [   0.00,    0.00,    0.00], 
              [   0.00,    0.00,    0.00], 
              [   0.00,    0.00,    0.00], 
              [   0.00,    0.00,    0.00], 
              [   0.00,    0.00,    0.00], 
              [   0.00,    0.00,    0.00], 
              [   0.00,    0.00,    0.00], 
              [   0.00,    0.00,    0.00], 
              [   0.00,    0.00,    0.00], 
              [   0.00,    0.00,    0.00], 
              [   0.00,    0.00,    0.00], 
              [   0.00,    0.00,    0.00], 
              [   0.00,    0.00,    0.00], 
              [   0.00,    0.00,    0.00], 
              [   0.00,    0.00,    0.00], 
              [   0.00,    0.00,    0.00], 
              [   0.00,    0.00,    0.00], 
              [   0.00,    0.00,    0.00], 
              [   0.00,    0.00,    0.00], 
              [   0.00,    0.00,    0.00], 
              [   0.00,    0.00,    0.00], 
              [   0.00,    0.00,    0.00], 
              [   0.00,    0.00,    0.00], 
              [   0.00,    0.00,    0.00], 
              [   0.00,    0.00,    0.00], 
              [   0.00,    0.00,    0.00], 
              [   0.00,    0.00,    0.00], 
              [   0.00,    0.00,    0.00], 
              [   0.00,    0.00,    0.00], 
              [   0.00,    0.00,    0.00], 
              [   0.00,    0.00,    0.00], 
              [   0.00,    0.00,    0.00], 
              [   0.00,    0.00,    0.00], 
              [   0.00,    0.00,    0.00], 
              [   0.00,    0.00,    0.00], 
              [   0.00,    0.00,    0.00], 
              [   0.00,    0.00,    0.00], 
              [   0.00,    0.00,    0.00], 
              [   0.00,    0.00,    0.00], 
              [   0.00,    0.00,    0.00], 
              [   0.00,    0.00,    0.00], 
              [   0.00,    0.00,    0.00], 
              [   0.00,    0.00,    0.00], 
              [   0.00,    0.00,    0.00], 
              [   0.00,    0.00,    0.00], 
              [   0.00,    0.00,    0.00], 
              [   0.00,    0.00,    0.00], 
              [   0.00,    0.00,    0.00], 
              [   0.00,    0.00,    0.00], 
              [   0.00,    0.00,    0.00], 
              [   0.00,    0.00,    0.00], 
              [   0.00,    0.00,    0.00], 
              [   0.00,    0.00,    0.00], 
              [   0.00,    0.00,    0.00], 
              [   0.00,    0.00,    0.00], 
              [   0.00,    0.00,    0.00], 
              [   0.00,    0.00,    0.00], 
              [   0.00,    0.00,    0.00], 
              [   0.00,    0.00,    0.00], 
              [   0.00,    0.00,    0.00], 
              [   0.00,    0.00,    0.00], 
              [   0.00,    0.00,    0.00], 
              [   0.00,    0.00,    0.00], 
              [   0.00,    0.00,    0.00], 
              [   0.00,    0.00,    0.00], 
              [   0.00,    0.00,    0.00], 
              [   0.00,    0.00,    0.00], 
              [   0.00,    0.00,    0.00], 
              [   0.00,    0.00,    0.00], 
              [   0.00,    0.00,    0.00], 
              [   0.00,    0.00,    0.00], 
              [   0.00,    0.00,    0.00], 
              [   0.00,    0.00,    0.00], 
              [   0.00,    0.00,    0.00], 
              [   0.00,    0.00,    0.00], 
              [   0.00,    0.00,    0.00], 
              [   0.00,    0.00,    0.00], 
              [   0.00,    0.00,    0.00], 
              [   0.00,    0.00,    0.00], 
              [   0.00,    0.00,    0.00], 
              [   0.00,    0.00,    0.00], 
              [   0.00,    0.00,    0.00], 
              [   0.00,    0.00,    0.00], 
              [   0.00,    0.00,    0.00], 
              [   0.00,    0.00,    0.00], 
              [   0.00,    0.00,    0.00], 
              [   0.00,    0.00,    0.00], 
              [   0.00,    0.00,    0.00], 
              [   0.00,    0.00,    0.00], 
              [   0.00,    0.00,    0.00], 
              [   0.00,    0.00,    0.00], 
              [   0.00,    0.00,    0.00], 
              [   0.00,    0.00,    0.00], 
              [   0.00,    0.00,    0.00], 
              [   0.00,    0.00,    0.00], 
              [   0.00,    0.00,    0.00], 
              [   0.00,    0.00,    0.00], 
              [   0.00,    0.00,    0.00], 
              [   0.00,    0.00,    0.00], 
              [   0.00,    0.00,    0.00], 
              [   0.00,    0.00,    0.00], 
              [   0.00,    0.00,    0.00], 
              [   0.00,    0.00,    0.00], 
              [   0.00,    0.00,    0.00], 
              [   0.00,    0.00,    0.00], 
              [   0.00,    0.00,    0.00], 
              [   0.00,    0.00,    0.00], 
              [   0.00,    0.00,    0.00], 
              [   0.00,    0.00,    0.00], 
              [   0.00,    0.00,    0.00], 
              [   0.00,    0.00,    0.00], 
              [   0.00,    0.00,    0.00], 
              [   0.00,    0.00,    0.00], 
              [   0.00,    0.00,    0.00], 
              [   0.00,    0.00,    0.00], 
              [   0.00,    0.00,    0.00], 
              [   0.00,    0.00,    0.00], 
              [   0.00,    0.00,    0.00], 
              [   0.00,    0.00,    0.00], 
              [   0.00,    0.00,    0.00], 
              [   0.00,    0.00,    0.00], 
              [   0.00,    0.00,    0.00], 
              [   0.00,    0.00,    0.00], 
              [   0.00,    0.00,    0.00], 
              [   0.00,    0.00,    0.00], 
              [   0.00,    0.00,    0.00], 
              [   0.00,    0.00,    0.00], 
              [   0.00,    0.00,    0.00], 
              [   0.00,    0.00,    0.00], 
              [   0.00,    0.00,    0.00], 
              [   0.00,    0.00,    0.00], 
              [   0.00,    0.00,    0.00], 
              [   0.00,    0.00,    0.00], 
              [   0.00,    0.00,    0.00], 
              [   0.00,    0.00,    0.00], 
              [   0.00,    0.00,    0.00], 
              [   0.00,    0.00,    0.00], 
              [   0.00,    0.00,    0.00], 
              [   0.00,    0.00,    0.00], 
              [   0.00,    0.00,    0.00], 
              [   0.00,    0.00,    0.00], 
              [   0.00,    0.00,    0.00], 
              [   0.00,    0.00,    0.00], 
              [   0.00,    0.00,    0.00], 
              [   0.00,    0.00,    0.00], 
              [   0.00,    0.00,    0.00], 
              [   0.00,    0.00,    0.00], 
              [   0.00,    0.00,    0.00], 
              [   0.00,    0.00,    0.00], 
              [   0.00,    0.00,    0.00], 
              [   0.00,    0.00,    0.00], 
              [   0.00,    0.00,    0.00], 
              [   0.00,    0.00,    0.00], 
              [   0.00,    0.00,    0.00], 
              [   0.00,    0.00,    0.00], 
              [   0.00,    0.00,    0.00], 
              [   0.00,    0.00,    0.00], 
              [   0.00,    0.00,    0.00], 
              [   0.00,    0.00,    0.00], 
              [   0.00,    0.00,    0.00], 
              [   0.00,    0.00,    0.00], 
              [   0.00,    0.00,    0.00], 
              [   0.00,    0.00,    0.00], 
              [   0.00,    0.00,    0.00], 
              [   0.00,    0.00,    0.00], 
              [   0.00,    0.00,    0.00], 
              [   0.00,    0.00,    0.00], 
              [   0.00,    0.00,    0.00], 
              [   0.00,    0.00,    0.00], 
              [   0.00,    0.00,    0.00], 
              [   0.00,    0.00,    0.00], 
              [   0.00,    0.00,    0.00], 
              [   0.00,    0.00,    0.00], 
              [   0.00,    0.00,    0.00], 
              [   0.00,    0.00,    0.00], 
              [   0.00,    0.00,    0.00], 
              [   0.00,    0.00,    0.00], 
              [   0.00,    0.00,    0.00], 
              [   0.00,    0.00,    0.00], 
              [   0.00,    0.00,    0.00], 
              [   0.00,    0.00,    0.00], 
              [   0.00,    0.00,    0.00], 
              [   0.00,    0.00,    0.00], 
              [   0.00,    0.00,    0.00], 
              [   0.00,    0.00,    0.00], 
              [   0.00,    0.00,    0.00], 
              [   0.00,    0.00,    0.00], 
              [   0.00,    0.00,    0.00], 
              [   0.00,    0.00,    0.00], 
              [   0.00,    0.00,    0.00], 
              [   0.00,    0.00,    0.00], 
              [   0.00,    0.00,    0.00], 
              [   0.00,    0.00,    0.00], 
              [   0.00,    0.00,    0.00], 
              [   0.00,    0.00,    0.00], 
              [   0.00,    0.00,    0.00], 
              [   0.00,    0.00,    0.00], 
              [   0.00,    0.00,    0.00], 
              [   0.00,    0.00,    0.00], 
              [   0.00,    0.00,    0.00], 
              [   0.00,    0.00,    0.00], 
              [   0.00,    0.00,    0.00], 
              [   0.00,    0.00,    0.00], 
              [   0.00,    0.00,    0.00], 
              [   0.00,    0.00,    0.00], 
              [   0.00,    0.00,    0.00], 
              [   0.00,    0.00,    0.00], 
              [   0.00,    0.00,    0.00], 
              [   0.00,    0.00,    0.00], 
              [   0.00,    0.00,    0.00], 
              [   0.00,    0.00,    0.00], 
              [   0.00,    0.00,    0.00], 
              [   0.00,    0.00,    0.00], 
              [   0.00,    0.00,    0.00], 
              [   0.00,    0.00,    0.00], 
              [   0.00,    0.00,    0.00], 
              [   0.00,    0.00,    0.00], 
              [   0.00,    0.00,    0.00], 
              [   0.00,    0.00,    0.00], 
              [   0.00,    0.00,    0.00], 
              [   0.00,    0.00,    0.00], 
              [   0.00,    0.00,    0.00], 
              [   0.00,    0.00,    0.00], 
              [   0.00,    0.00,    0.00], 
              [   0.00,    0.00,    0.00], 
              [   0.00,    0.00,    0.00], 
              [   0.00,    0.00,    0.00], 
              [   0.00,    0.00,    0.00], 
              [   0.00,    0.00,    0.00], 
              [   0.00,    0.00,    0.00], 
              [   0.00,    0.00,    0.00], 
              [   0.00,    0.00,    0.00], 
              [   0.00,    0.00,    0.00], 
              [   0.00,    0.00,    0.00], 
              [   0.00,    0.00,    0.00], 
              [   0.00,    0.00,    0.00], 
              [   0.00,    0.00,    0.00], 
              [   0.00,    0.00,    0.00], 
              [   0.00,    0.00,    0.00], 
              [   0.00,    0.00,    0.00], 
              [   0.00,    0.00,    0.00], 
              [   0.00,    0.00,    0.00], 
              [   0.00,    0.00,    0.00], 
              [   0.00,    0.00,    0.00], 
              [   0.00,    0.00,    0.00], 
              [   0.00,    0.00,    0.00], 
              [   0.00,    0.00,    0.00], 
              [   0.00,    0.00,    0.00], 
              [   0.00,    0.00,    0.00], 
              [   0.00,    0.00,    0.00], 
              [   0.00,    0.00,    0.00], 
              [   0.00,    0.00,    0.00], 
              [   0.00,    0.00,    0.00], 
              [   0.00,    0.00,    0.00], 
              [   0.00,    0.00,    0.00], 
              [   0.00,    0.00,    0.00], 
              [   0.00,    0.00,    0.00], 
              [   0.00,    0.00,    0.00], 
              [   0.00,    0.00,    0.00], 
              [   0.00,    0.00,    0.00], 
              [   0.00,    0.00,    0.00], 
              [   0.00,    0.00,    0.00], 
              [   0.00,    0.00,    0.00], 
              [   0.00,    0.00,    0.00], 
              [   0.00,    0.00,    0.00], 
              [   0.00,    0.00,    0.00], 
              [   0.00,    0.00,    0.00], 
              [   0.00,    0.00,    0.00], 
              [   0.00,    0.00,    0.00], 
              [   0.00,    0.00,    0.00], 
              [   0.00,    0.00,    0.00], 
              [   0.00,    0.00,    0.00], 
              [   0.00,    0.00,    0.00], 
              [   0.00,    0.00,    0.00], 
              [   0.00,    0.00,    0.00], 
              [   0.00,    0.00,    0.00], 
              [   0.00,    0.00,    0.00], 
              [   0.00,    0.00,    0.00], 
              [   0.00,    0.00,    0.00], 
              [   0.00,    0.00,    0.00], 
              [   0.00,    0.00,    0.00], 
              [   0.00,    0.00,    0.00], 
              [   0.00,    0.00,    0.00], 
              [   0.00,    0.00,    0.00], 
              [   0.00,    0.00,    0.00], 
              [   0.00,    0.00,    0.00], 
              [   0.00,    0.00,    0.00], 
              [   0.00,    0.00,    0.00], 
              [   0.00,    0.00,    0.00], 
              [   0.00,    0.00,    0.00], 
              [   0.00,    0.00,    0.00], 
              [   0.00,    0.00,    0.00], 
              [   0.00,    0.00,    0.00], 
              [   0.00,    0.00,    0.00], 
              [   0.00,    0.00,    0.00], 
              [   0.00,    0.00,    0.00], 
              [   0.00,    0.00,    0.00], 
              [   0.00,    0.00,    0.00], 
              [   0.00,    0.00,    0.00], 
              [   0.00,    0.00,    0.00], 
              [   0.00,    0.00,    0.00], 
              [   0.00,    0.00,    0.00], 
              [   0.00,    0.00,    0.00], 
              [   0.00,    0.00,    0.00], 
              [   0.00,    0.00,    0.00], 
              [   0.00,    0.00,    0.00], 
              [   0.00,    0.00,    0.00], 
              [   0.00,    0.00,    0.00], 
              [   0.00,    0.00,    0.00], 
              [   0.00,    0.00,    0.00], 
              [   0.00,    0.00,    0.00], 
              [   0.00,    0.00,    0.00], 
              [   0.00,    0.00,    0.00], 
              [   0.00,    0.00,    0.00], 
              [   0.00,    0.00,    0.00], 
              [   0.00,    0.00,    0.00], 
              [   0.00,    0.00,    0.00], 
              [   0.00,    0.00,    0.00], 
              [   0.00,    0.00,    0.00], 
              [   0.00,    0.00,    0.00], 
              [   0.00,    0.00,    0.00], 
              [   0.00,    0.00,    0.00], 
              [   0.00,    0.00,    0.00], 
              [   0.00,    0.00,    0.00], 
              [   0.00,    0.00,    0.00], 
              [   0.00,    0.00,    0.00], 
              [   0.00,    0.00,    0.00], 
              [   0.00,    0.00,    0.00], 
              [   0.00,    0.00,    0.00], 
              [   0.00,    0.00,    0.00], 
              [   0.00,    0.00,    0.00], 
              [   0.00,    0.00,    0.00], 
              [   0.00,    0.00,    0.00], 
              [   0.00,    0.00,    0.00], 
              [   0.00,    0.00,    0.00], 
              [   0.00,    0.00,    0.00], 
              [   0.00,    0.00,    0.00], 
              [   0.00,    0.00,    0.00], 
              [   0.00,    0.00,    0.00], 
              [   0.00,    0.00,    0.00], 
              [   0.00,    0.00,    0.00], 
              [   0.00,    0.00,    0.00], 
              [   0.00,    0.00,    0.00], 
              [   0.00,    0.00,    0.00], 
              [   0.00,    0.00,    0.00], 
              [   0.00,    0.00,    0.00], 
              [   0.00,    0.00,    0.00], 
              [   0.00,    0.00,    0.00], 
              [   0.00,    0.00,    0.00], 
              [   0.00,    0.00,    0.00], 
              [   0.00,    0.00,    0.00], 
              [   0.00,    0.00,    0.00], 
              [   0.00,    0.00,    0.00], 
              [   0.00,    0.00,    0.00], 
              [   0.00,    0.00,    0.00], 
              [   0.00,    0.00,    0.00], 
              [   0.00,    0.00,    0.00], 
              [   0.00,    0.00,    0.00], 
              [   0.00,    0.00,    0.00], 
              [   0.00,    0.00,    0.00], 
              [   0.00,    0.00,    0.00], 
              [   0.00,    0.00,    0.00], 
              [   0.00,    0.00,    0.00], 
              [   0.00,    0.00,    0.00], 
              [   0.00,    0.00,    0.00], 
              [   0.00,    0.00,    0.00], 
              [   0.00,    0.00,    0.00], 
              [   0.00,    0.00,    0.00], 
              [   0.00,    0.00,    0.00], 
              [   0.00,    0.00,    0.00], 
              [   0.00,    0.00,    0.00], 
              [   0.00,    0.00,    0.00], 
              [   0.00,    0.00,    0.00], 
              [   0.00,    0.00,    0.00], 
              [   0.00,    0.00,    0.00], 
              [   0.00,    0.00,    0.00], 
              [   0.00,    0.00,    0.00], 
              [   0.00,    0.00,    0.00], 
              [   0.00,    0.00,    0.00], 
              [   0.00,    0.00,    0.00], 
              [   0.00,    0.00,    0.00], 
              [   0.00,    0.00,    0.00], 
              [   0.00,    0.00,    0.00], 
              [   0.00,    0.00,    0.00], 
              [   0.00,    0.00,    0.00], 
              [   0.00,    0.00,    0.00], 
              [   0.00,    0.00,    0.00], 
              [   0.00,    0.00,    0.00], 
              [   0.00,    0.00,    0.00], 
              [   0.00,    0.00,    0.00], 
              [   0.00,    0.00,    0.00], 
              [   0.00,    0.00,    0.00], 
              [   0.00,    0.00,    0.00], 
              [   0.00,    0.00,    0.00], 
              [   0.00,    0.00,    0.00], 
              [   0.00,    0.00,    0.00], 
              [   0.00,    0.00,    0.00], 
              [   0.00,    0.00,    0.00], 
              [   0.00,    0.00,    0.00], 
              [   0.00,    0.00,    0.00], 
              [   0.00,    0.00,    0.00], 
              [   0.00,    0.00,    0.00], 
              [   0.00,    0.00,    0.00], 
              [   0.00,    0.00,    0.00], 
              [   0.00,    0.00,    0.00], 
              [   0.00,    0.00,    0.00], 
              [   0.00,    0.00,    0.00], 
              [   0.00,    0.00,    0.00], 
              [   0.00,    0.00,    0.00], 
              [   0.00,    0.00,    0.00], 
              [   0.00,    0.00,    0.00], 
              [   0.00,    0.00,    0.00], 
              [   0.00,    0.00,    0.00], 
              [   0.00,    0.00,    0.00], 
              [   0.00,    0.00,    0.00], 
              [   0.00,    0.00,    0.00], 
              [   0.00,    0.00,    0.00], 
              [   0.00,    0.00,    0.00], 
              [   0.00,    0.00,    0.00], 
              [   0.00,    0.00,    0.00], 
              [   0.00,    0.00,    0.00], 
              [   0.00,    0.00,    0.00], 
              [   0.00,    0.00,    0.00], 
              [   0.00,    0.00,    0.00], 
              [   0.00,    0.00,    0.00], 
              [   0.00,    0.00,    0.00], 
              [   0.00,    0.00,    0.00], 
              [   0.00,    0.00,    0.00], 
              [   0.00,    0.00,    0.00], 
              [   0.00,    0.00,    0.00], 
              [   0.00,    0.00,    0.00], 
              [   0.00,    0.00,    0.00], 
              [   0.00,    0.00,    0.00], 
              [   0.00,    0.00,    0.00]
            ],
            "isKeyframe": false
        }
    ],
    "isKeyframe": false
}

