{
    "filename": "1/000388.jpg",
    "height": 3008,
    "width": 4128,
    "annots": [
        {
            "personID": 0,
            "bbox": [1880.82, 1793.78, 2294.68, 3002.10, 0.70],
            "bbox_handl2d": [0.00, 0.00, 100.00, 100.00, 0.00],
            "bbox_handr2d": [0.00, 0.00, 100.00, 100.00, 0.00],
            "bbox_face2d": [0.00, 0.00, 100.00, 100.00, 0.00],
            "keypoints": [
              [2253.24, 1934.20,    0.98], 
              [2131.86, 2000.01,    1.00], 
              [2187.97, 2042.71,    1.00], 
              [2148.11, 2239.08,    0.47], 
              [2144.25, 2296.41,    0.44], 
              [2075.76, 1957.30,    1.00], 
              [2003.58, 2109.04,    0.08], 
              [2254.99, 2242.59,    0.17], 
              [1968.40, 2323.28,    1.00], 
              [2021.50, 2344.79,    1.00], 
              [2064.31, 2574.80,    0.86], 
              [2055.34, 2832.37,    0.85], 
              [1915.31, 2301.77,    1.00], 
              [2008.98, 2457.23,    0.12], 
              [2006.82, 2618.57,    0.31], 
              [2260.19, 1910.79,    0.99], 
              [2243.80, 1901.60,    0.97], 
              [2248.99, 1911.06,    0.99], 
              [2211.43, 1894.48,    0.99], 
              [2062.64, 2663.16,    0.29], 
              [2062.64, 2663.16,    0.29], 
              [1988.16, 2644.74,    0.41], 
              [2105.30, 2901.41,    0.76], 
              [2105.30, 2901.41,    0.76], 
              [2016.70, 2881.66,    0.73]
            ],
            "handl2d": [
              [   0.00,    0.00,    0.00], 
              [   0.00,    0.00,    0.00], 
              [   0.00,    0.00,    0.00], 
              [   0.00,    0.00,    0.00], 
              [   0.00,    0.00,    0.00], 
              [   0.00,    0.00,    0.00], 
              [   0.00,    0.00,    0.00], 
              [   0.00,    0.00,    0.00], 
              [   0.00,    0.00,    0.00], 
              [   0.00,    0.00,    0.00], 
              [   0.00,    0.00,    0.00], 
              [   0.00,    0.00,    0.00], 
              [   0.00,    0.00,    0.00], 
              [   0.00,    0.00,    0.00], 
              [   0.00,    0.00,    0.00], 
              [   0.00,    0.00,    0.00], 
              [   0.00,    0.00,    0.00], 
              [   0.00,    0.00,    0.00], 
              [   0.00,    0.00,    0.00], 
              [   0.00,    0.00,    0.00], 
              [   0.00,    0.00,    0.00]
            ],
            "handr2d": [
              [   0.00,    0.00,    0.00], 
              [   0.00,    0.00,    0.00], 
              [   0.00,    0.00,    0.00], 
              [   0.00,    0.00,    0.00], 
              [   0.00,    0.00,    0.00], 
              [   0.00,    0.00,    0.00], 
              [   0.00,    0.00,    0.00], 
              [   0.00,    0.00,    0.00], 
              [   0.00,    0.00,    0.00], 
              [   0.00,    0.00,    0.00], 
              [   0.00,    0.00,    0.00], 
              [   0.00,    0.00,    0.00], 
              [   0.00,    0.00,    0.00], 
              [   0.00,    0.00,    0.00], 
              [   0.00,    0.00,    0.00], 
              [   0.00,    0.00,    0.00], 
              [   0.00,    0.00,    0.00], 
              [   0.00,    0.00,    0.00], 
              [   0.00,    0.00,    0.00], 
              [   0.00,    0.00,    0.00], 
              [   0.00,    0.00,    0.00]
            ],
            "face2d": [
              [   0.00,    0.00,    0.00], 
              [   0.00,    0.00,    0.00], 
              [   0.00,    0.00,    0.00], 
              [   0.00,    0.00,    0.00], 
              [   0.00,    0.00,    0.00], 
              [   0.00,    0.00,    0.00], 
              [   0.00,    0.00,    0.00], 
              [   0.00,    0.00,    0.00], 
              [   0.00,    0.00,    0.00], 
              [   0.00,    0.00,    0.00], 
              [   0.00,    0.00,    0.00], 
              [   0.00,    0.00,    0.00], 
              [   0.00,    0.00,    0.00], 
              [   0.00,    0.00,    0.00], 
              [   0.00,    0.00,    0.00], 
              [   0.00,    0.00,    0.00], 
              [   0.00,    0.00,    0.00], 
              [   0.00,    0.00,    0.00], 
              [   0.00,    0.00,    0.00], 
              [   0.00,    0.00,    0.00], 
              [   0.00,    0.00,    0.00], 
              [   0.00,    0.00,    0.00], 
              [   0.00,    0.00,    0.00], 
              [   0.00,    0.00,    0.00], 
              [   0.00,    0.00,    0.00], 
              [   0.00,    0.00,    0.00], 
              [   0.00,    0.00,    0.00], 
              [   0.00,    0.00,    0.00], 
              [   0.00,    0.00,    0.00], 
              [   0.00,    0.00,    0.00], 
              [   0.00,    0.00,    0.00], 
              [   0.00,    0.00,    0.00], 
              [   0.00,    0.00,    0.00], 
              [   0.00,    0.00,    0.00], 
              [   0.00,    0.00,    0.00], 
              [   0.00,    0.00,    0.00], 
              [   0.00,    0.00,    0.00], 
              [   0.00,    0.00,    0.00], 
              [   0.00,    0.00,    0.00], 
              [   0.00,    0.00,    0.00], 
              [   0.00,    0.00,    0.00], 
              [   0.00,    0.00,    0.00], 
              [   0.00,    0.00,    0.00], 
              [   0.00,    0.00,    0.00], 
              [   0.00,    0.00,    0.00], 
              [   0.00,    0.00,    0.00], 
              [   0.00,    0.00,    0.00], 
              [   0.00,    0.00,    0.00], 
              [   0.00,    0.00,    0.00], 
              [   0.00,    0.00,    0.00], 
              [   0.00,    0.00,    0.00], 
              [   0.00,    0.00,    0.00], 
              [   0.00,    0.00,    0.00], 
              [   0.00,    0.00,    0.00], 
              [   0.00,    0.00,    0.00], 
              [   0.00,    0.00,    0.00], 
              [   0.00,    0.00,    0.00], 
              [   0.00,    0.00,    0.00], 
              [   0.00,    0.00,    0.00], 
              [   0.00,    0.00,    0.00], 
              [   0.00,    0.00,    0.00], 
              [   0.00,    0.00,    0.00], 
              [   0.00,    0.00,    0.00], 
              [   0.00,    0.00,    0.00], 
              [   0.00,    0.00,    0.00], 
              [   0.00,    0.00,    0.00], 
              [   0.00,    0.00,    0.00], 
              [   0.00,    0.00,    0.00], 
              [   0.00,    0.00,    0.00], 
              [   0.00,    0.00,    0.00], 
              [   0.00,    0.00,    0.00], 
              [   0.00,    0.00,    0.00], 
              [   0.00,    0.00,    0.00], 
              [   0.00,    0.00,    0.00], 
              [   0.00,    0.00,    0.00], 
              [   0.00,    0.00,    0.00], 
              [   0.00,    0.00,    0.00], 
              [   0.00,    0.00,    0.00], 
              [   0.00,    0.00,    0.00], 
              [   0.00,    0.00,    0.00], 
              [   0.00,    0.00,    0.00], 
              [   0.00,    0.00,    0.00], 
              [   0.00,    0.00,    0.00], 
              [   0.00,    0.00,    0.00], 
              [   0.00,    0.00,    0.00], 
              [   0.00,    0.00,    0.00], 
              [   0.00,    0.00,    0.00], 
              [   0.00,    0.00,    0.00], 
              [   0.00,    0.00,    0.00], 
              [   0.00,    0.00,    0.00], 
              [   0.00,    0.00,    0.00], 
              [   0.00,    0.00,    0.00], 
              [   0.00,    0.00,    0.00], 
              [   0.00,    0.00,    0.00], 
              [   0.00,    0.00,    0.00], 
              [   0.00,    0.00,    0.00], 
              [   0.00,    0.00,    0.00], 
              [   0.00,    0.00,    0.00], 
              [   0.00,    0.00,    0.00], 
              [   0.00,    0.00,    0.00], 
              [   0.00,    0.00,    0.00], 
              [   0.00,    0.00,    0.00], 
              [   0.00,    0.00,    0.00], 
              [   0.00,    0.00,    0.00], 
              [   0.00,    0.00,    0.00], 
              [   0.00,    0.00,    0.00], 
              [   0.00,    0.00,    0.00], 
              [   0.00,    0.00,    0.00], 
              [   0.00,    0.00,    0.00], 
              [   0.00,    0.00,    0.00], 
              [   0.00,    0.00,    0.00], 
              [   0.00,    0.00,    0.00], 
              [   0.00,    0.00,    0.00], 
              [   0.00,    0.00,    0.00], 
              [   0.00,    0.00,    0.00], 
              [   0.00,    0.00,    0.00], 
              [   0.00,    0.00,    0.00], 
              [   0.00,    0.00,    0.00], 
              [   0.00,    0.00,    0.00], 
              [   0.00,    0.00,    0.00], 
              [   0.00,    0.00,    0.00], 
              [   0.00,    0.00,    0.00], 
              [   0.00,    0.00,    0.00], 
              [   0.00,    0.00,    0.00], 
              [   0.00,    0.00,    0.00], 
              [   0.00,    0.00,    0.00], 
              [   0.00,    0.00,    0.00], 
              [   0.00,    0.00,    0.00], 
              [   0.00,    0.00,    0.00], 
              [   0.00,    0.00,    0.00], 
              [   0.00,    0.00,    0.00], 
              [   0.00,    0.00,    0.00], 
              [   0.00,    0.00,    0.00], 
              [   0.00,    0.00,    0.00], 
              [   0.00,    0.00,    0.00], 
              [   0.00,    0.00,    0.00], 
              [   0.00,    0.00,    0.00], 
              [   0.00,    0.00,    0.00], 
              [   0.00,    0.00,    0.00], 
              [   0.00,    0.00,    0.00], 
              [   0.00,    0.00,    0.00], 
              [   0.00,    0.00,    0.00], 
              [   0.00,    0.00,    0.00], 
              [   0.00,    0.00,    0.00], 
              [   0.00,    0.00,    0.00], 
              [   0.00,    0.00,    0.00], 
              [   0.00,    0.00,    0.00], 
              [   0.00,    0.00,    0.00], 
              [   0.00,    0.00,    0.00], 
              [   0.00,    0.00,    0.00], 
              [   0.00,    0.00,    0.00], 
              [   0.00,    0.00,    0.00], 
              [   0.00,    0.00,    0.00], 
              [   0.00,    0.00,    0.00], 
              [   0.00,    0.00,    0.00], 
              [   0.00,    0.00,    0.00], 
              [   0.00,    0.00,    0.00], 
              [   0.00,    0.00,    0.00], 
              [   0.00,    0.00,    0.00], 
              [   0.00,    0.00,    0.00], 
              [   0.00,    0.00,    0.00], 
              [   0.00,    0.00,    0.00], 
              [   0.00,    0.00,    0.00], 
              [   0.00,    0.00,    0.00], 
              [   0.00,    0.00,    0.00], 
              [   0.00,    0.00,    0.00], 
              [   0.00,    0.00,    0.00], 
              [   0.00,    0.00,    0.00], 
              [   0.00,    0.00,    0.00], 
              [   0.00,    0.00,    0.00], 
              [   0.00,    0.00,    0.00], 
              [   0.00,    0.00,    0.00], 
              [   0.00,    0.00,    0.00], 
              [   0.00,    0.00,    0.00], 
              [   0.00,    0.00,    0.00], 
              [   0.00,    0.00,    0.00], 
              [   0.00,    0.00,    0.00], 
              [   0.00,    0.00,    0.00], 
              [   0.00,    0.00,    0.00], 
              [   0.00,    0.00,    0.00], 
              [   0.00,    0.00,    0.00], 
              [   0.00,    0.00,    0.00], 
              [   0.00,    0.00,    0.00], 
              [   0.00,    0.00,    0.00], 
              [   0.00,    0.00,    0.00], 
              [   0.00,    0.00,    0.00], 
              [   0.00,    0.00,    0.00], 
              [   0.00,    0.00,    0.00], 
              [   0.00,    0.00,    0.00], 
              [   0.00,    0.00,    0.00], 
              [   0.00,    0.00,    0.00], 
              [   0.00,    0.00,    0.00], 
              [   0.00,    0.00,    0.00], 
              [   0.00,    0.00,    0.00], 
              [   0.00,    0.00,    0.00], 
              [   0.00,    0.00,    0.00], 
              [   0.00,    0.00,    0.00], 
              [   0.00,    0.00,    0.00], 
              [   0.00,    0.00,    0.00], 
              [   0.00,    0.00,    0.00], 
              [   0.00,    0.00,    0.00], 
              [   0.00,    0.00,    0.00], 
              [   0.00,    0.00,    0.00], 
              [   0.00,    0.00,    0.00], 
              [   0.00,    0.00,    0.00], 
              [   0.00,    0.00,    0.00], 
              [   0.00,    0.00,    0.00], 
              [   0.00,    0.00,    0.00], 
              [   0.00,    0.00,    0.00], 
              [   0.00,    0.00,    0.00], 
              [   0.00,    0.00,    0.00], 
              [   0.00,    0.00,    0.00], 
              [   0.00,    0.00,    0.00], 
              [   0.00,    0.00,    0.00], 
              [   0.00,    0.00,    0.00], 
              [   0.00,    0.00,    0.00], 
              [   0.00,    0.00,    0.00], 
              [   0.00,    0.00,    0.00], 
              [   0.00,    0.00,    0.00], 
              [   0.00,    0.00,    0.00], 
              [   0.00,    0.00,    0.00], 
              [   0.00,    0.00,    0.00], 
              [   0.00,    0.00,    0.00], 
              [   0.00,    0.00,    0.00], 
              [   0.00,    0.00,    0.00], 
              [   0.00,    0.00,    0.00], 
              [   0.00,    0.00,    0.00], 
              [   0.00,    0.00,    0.00], 
              [   0.00,    0.00,    0.00], 
              [   0.00,    0.00,    0.00], 
              [   0.00,    0.00,    0.00], 
              [   0.00,    0.00,    0.00], 
              [   0.00,    0.00,    0.00], 
              [   0.00,    0.00,    0.00], 
              [   0.00,    0.00,    0.00], 
              [   0.00,    0.00,    0.00], 
              [   0.00,    0.00,    0.00], 
              [   0.00,    0.00,    0.00], 
              [   0.00,    0.00,    0.00], 
              [   0.00,    0.00,    0.00], 
              [   0.00,    0.00,    0.00], 
              [   0.00,    0.00,    0.00], 
              [   0.00,    0.00,    0.00], 
              [   0.00,    0.00,    0.00], 
              [   0.00,    0.00,    0.00], 
              [   0.00,    0.00,    0.00], 
              [   0.00,    0.00,    0.00], 
              [   0.00,    0.00,    0.00], 
              [   0.00,    0.00,    0.00], 
              [   0.00,    0.00,    0.00], 
              [   0.00,    0.00,    0.00], 
              [   0.00,    0.00,    0.00], 
              [   0.00,    0.00,    0.00], 
              [   0.00,    0.00,    0.00], 
              [   0.00,    0.00,    0.00], 
              [   0.00,    0.00,    0.00], 
              [   0.00,    0.00,    0.00], 
              [   0.00,    0.00,    0.00], 
              [   0.00,    0.00,    0.00], 
              [   0.00,    0.00,    0.00], 
              [   0.00,    0.00,    0.00], 
              [   0.00,    0.00,    0.00], 
              [   0.00,    0.00,    0.00], 
              [   0.00,    0.00,    0.00], 
              [   0.00,    0.00,    0.00], 
              [   0.00,    0.00,    0.00], 
              [   0.00,    0.00,    0.00], 
              [   0.00,    0.00,    0.00], 
              [   0.00,    0.00,    0.00], 
              [   0.00,    0.00,    0.00], 
              [   0.00,    0.00,    0.00], 
              [   0.00,    0.00,    0.00], 
              [   0.00,    0.00,    0.00], 
              [   0.00,    0.00,    0.00], 
              [   0.00,    0.00,    0.00], 
              [   0.00,    0.00,    0.00], 
              [   0.00,    0.00,    0.00], 
              [   0.00,    0.00,    0.00], 
              [   0.00,    0.00,    0.00], 
              [   0.00,    0.00,    0.00], 
              [   0.00,    0.00,    0.00], 
              [   0.00,    0.00,    0.00], 
              [   0.00,    0.00,    0.00], 
              [   0.00,    0.00,    0.00], 
              [   0.00,    0.00,    0.00], 
              [   0.00,    0.00,    0.00], 
              [   0.00,    0.00,    0.00], 
              [   0.00,    0.00,    0.00], 
              [   0.00,    0.00,    0.00], 
              [   0.00,    0.00,    0.00], 
              [   0.00,    0.00,    0.00], 
              [   0.00,    0.00,    0.00], 
              [   0.00,    0.00,    0.00], 
              [   0.00,    0.00,    0.00], 
              [   0.00,    0.00,    0.00], 
              [   0.00,    0.00,    0.00], 
              [   0.00,    0.00,    0.00], 
              [   0.00,    0.00,    0.00], 
              [   0.00,    0.00,    0.00], 
              [   0.00,    0.00,    0.00], 
              [   0.00,    0.00,    0.00], 
              [   0.00,    0.00,    0.00], 
              [   0.00,    0.00,    0.00], 
              [   0.00,    0.00,    0.00], 
              [   0.00,    0.00,    0.00], 
              [   0.00,    0.00,    0.00], 
              [   0.00,    0.00,    0.00], 
              [   0.00,    0.00,    0.00], 
              [   0.00,    0.00,    0.00], 
              [   0.00,    0.00,    0.00], 
              [   0.00,    0.00,    0.00], 
              [   0.00,    0.00,    0.00], 
              [   0.00,    0.00,    0.00], 
              [   0.00,    0.00,    0.00], 
              [   0.00,    0.00,    0.00], 
              [   0.00,    0.00,    0.00], 
              [   0.00,    0.00,    0.00], 
              [   0.00,    0.00,    0.00], 
              [   0.00,    0.00,    0.00], 
              [   0.00,    0.00,    0.00], 
              [   0.00,    0.00,    0.00], 
              [   0.00,    0.00,    0.00], 
              [   0.00,    0.00,    0.00], 
              [   0.00,    0.00,    0.00], 
              [   0.00,    0.00,    0.00], 
              [   0.00,    0.00,    0.00], 
              [   0.00,    0.00,    0.00], 
              [   0.00,    0.00,    0.00], 
              [   0.00,    0.00,    0.00], 
              [   0.00,    0.00,    0.00], 
              [   0.00,    0.00,    0.00], 
              [   0.00,    0.00,    0.00], 
              [   0.00,    0.00,    0.00], 
              [   0.00,    0.00,    0.00], 
              [   0.00,    0.00,    0.00], 
              [   0.00,    0.00,    0.00], 
              [   0.00,    0.00,    0.00], 
              [   0.00,    0.00,    0.00], 
              [   0.00,    0.00,    0.00], 
              [   0.00,    0.00,    0.00], 
              [   0.00,    0.00,    0.00], 
              [   0.00,    0.00,    0.00], 
              [   0.00,    0.00,    0.00], 
              [   0.00,    0.00,    0.00], 
              [   0.00,    0.00,    0.00], 
              [   0.00,    0.00,    0.00], 
              [   0.00,    0.00,    0.00], 
              [   0.00,    0.00,    0.00], 
              [   0.00,    0.00,    0.00], 
              [   0.00,    0.00,    0.00], 
              [   0.00,    0.00,    0.00], 
              [   0.00,    0.00,    0.00], 
              [   0.00,    0.00,    0.00], 
              [   0.00,    0.00,    0.00], 
              [   0.00,    0.00,    0.00], 
              [   0.00,    0.00,    0.00], 
              [   0.00,    0.00,    0.00], 
              [   0.00,    0.00,    0.00], 
              [   0.00,    0.00,    0.00], 
              [   0.00,    0.00,    0.00], 
              [   0.00,    0.00,    0.00], 
              [   0.00,    0.00,    0.00], 
              [   0.00,    0.00,    0.00], 
              [   0.00,    0.00,    0.00], 
              [   0.00,    0.00,    0.00], 
              [   0.00,    0.00,    0.00], 
              [   0.00,    0.00,    0.00], 
              [   0.00,    0.00,    0.00], 
              [   0.00,    0.00,    0.00], 
              [   0.00,    0.00,    0.00], 
              [   0.00,    0.00,    0.00], 
              [   0.00,    0.00,    0.00], 
              [   0.00,    0.00,    0.00], 
              [   0.00,    0.00,    0.00], 
              [   0.00,    0.00,    0.00], 
              [   0.00,    0.00,    0.00], 
              [   0.00,    0.00,    0.00], 
              [   0.00,    0.00,    0.00], 
              [   0.00,    0.00,    0.00], 
              [   0.00,    0.00,    0.00], 
              [   0.00,    0.00,    0.00], 
              [   0.00,    0.00,    0.00], 
              [   0.00,    0.00,    0.00], 
              [   0.00,    0.00,    0.00], 
              [   0.00,    0.00,    0.00], 
              [   0.00,    0.00,    0.00], 
              [   0.00,    0.00,    0.00], 
              [   0.00,    0.00,    0.00], 
              [   0.00,    0.00,    0.00], 
              [   0.00,    0.00,    0.00], 
              [   0.00,    0.00,    0.00], 
              [   0.00,    0.00,    0.00], 
              [   0.00,    0.00,    0.00], 
              [   0.00,    0.00,    0.00], 
              [   0.00,    0.00,    0.00], 
              [   0.00,    0.00,    0.00], 
              [   0.00,    0.00,    0.00], 
              [   0.00,    0.00,    0.00], 
              [   0.00,    0.00,    0.00], 
              [   0.00,    0.00,    0.00], 
              [   0.00,    0.00,    0.00], 
              [   0.00,    0.00,    0.00], 
              [   0.00,    0.00,    0.00], 
              [   0.00,    0.00,    0.00], 
              [   0.00,    0.00,    0.00], 
              [   0.00,    0.00,    0.00], 
              [   0.00,    0.00,    0.00], 
              [   0.00,    0.00,    0.00], 
              [   0.00,    0.00,    0.00], 
              [   0.00,    0.00,    0.00], 
              [   0.00,    0.00,    0.00], 
              [   0.00,    0.00,    0.00], 
              [   0.00,    0.00,    0.00], 
              [   0.00,    0.00,    0.00], 
              [   0.00,    0.00,    0.00], 
              [   0.00,    0.00,    0.00], 
              [   0.00,    0.00,    0.00], 
              [   0.00,    0.00,    0.00], 
              [   0.00,    0.00,    0.00], 
              [   0.00,    0.00,    0.00], 
              [   0.00,    0.00,    0.00], 
              [   0.00,    0.00,    0.00], 
              [   0.00,    0.00,    0.00], 
              [   0.00,    0.00,    0.00], 
              [   0.00,    0.00,    0.00], 
              [   0.00,    0.00,    0.00], 
              [   0.00,    0.00,    0.00], 
              [   0.00,    0.00,    0.00], 
              [   0.00,    0.00,    0.00], 
              [   0.00,    0.00,    0.00], 
              [   0.00,    0.00,    0.00], 
              [   0.00,    0.00,    0.00], 
              [   0.00,    0.00,    0.00], 
              [   0.00,    0.00,    0.00], 
              [   0.00,    0.00,    0.00], 
              [   0.00,    0.00,    0.00], 
              [   0.00,    0.00,    0.00], 
              [   0.00,    0.00,    0.00], 
              [   0.00,    0.00,    0.00], 
              [   0.00,    0.00,    0.00], 
              [   0.00,    0.00,    0.00], 
              [   0.00,    0.00,    0.00], 
              [   0.00,    0.00,    0.00], 
              [   0.00,    0.00,    0.00], 
              [   0.00,    0.00,    0.00], 
              [   0.00,    0.00,    0.00], 
              [   0.00,    0.00,    0.00], 
              [   0.00,    0.00,    0.00], 
              [   0.00,    0.00,    0.00], 
              [   0.00,    0.00,    0.00], 
              [   0.00,    0.00,    0.00], 
              [   0.00,    0.00,    0.00], 
              [   0.00,    0.00,    0.00], 
              [   0.00,    0.00,    0.00], 
              [   0.00,    0.00,    0.00], 
              [   0.00,    0.00,    0.00], 
              [   0.00,    0.00,    0.00], 
              [   0.00,    0.00,    0.00], 
              [   0.00,    0.00,    0.00], 
              [   0.00,    0.00,    0.00], 
              [   0.00,    0.00,    0.00], 
              [   0.00,    0.00,    0.00], 
              [   0.00,    0.00,    0.00], 
              [   0.00,    0.00,    0.00], 
              [   0.00,    0.00,    0.00], 
              [   0.00,    0.00,    0.00], 
              [   0.00,    0.00,    0.00], 
              [   0.00,    0.00,    0.00]
            ],
            "isKeyframe": false
        }
    ],
    "isKeyframe": false
}

